{
	"description": "A WePY project",
	"setting": {
		"urlCheck": false,
		"es6": false,
		"postcss": false,
		"minified": false,
		"newFeature": true,
		"autoAudits": false
	},
	"compileType": "miniprogram",
	"appid": "wxfd2614fc306b7c65",
	"projectname": "myproj",
	"miniprogramRoot": "dist/",
	"condition": {
		"search": {
			"current": -1,
			"list": []
		},
		"conversation": {
			"current": -1,
			"list": []
		},
		"plugin": {
			"current": -1,
			"list": []
		},
		"game": {
			"list": []
		},
		"miniprogram": {
			"current": 1,
			"list": [
				{
					"id": -1,
					"name": "分类页面的开发",
					"pathName": "pages/tabs/cates",
					"query": "",
					"scene": null
				},
				{
					"id": -1,
					"name": "index",
					"pathName": "pages/index",
					"scene": null
				}
			]
		}
	}
}